rakam_systems/__init__.py
rakam_systems/components/__init__.py
rakam_systems/components/agents/__init__.py
rakam_systems/components/agents/actions.py
rakam_systems/components/agents/agents.py
rakam_systems/components/base.py
rakam_systems/components/data_processing/__init__.py
rakam_systems/components/data_processing/content_extractors.py
rakam_systems/components/data_processing/data_processor.py
rakam_systems/components/data_processing/node_processors.py
rakam_systems/components/data_processing/utils.py
rakam_systems/components/rag/__init__.py
rakam_systems/components/vector_search/__init__.py
rakam_systems/components/vector_search/vector_store.py
rakam_systems/core.py
rakam_systems/custom_loggers.py
rakam_systems/template_systems/agent.py
rakam_systems/template_systems/rag.py
rakam_systems/tutorials/__init__.py
rakam_systems/tutorials/simple_agent.py
rakam_systems/tutorials/simple_rag.py
rakam_systems-0.1.4.dist-info/LICENSE
rakam_systems-0.1.4.dist-info/METADATA
rakam_systems-0.1.4.dist-info/WHEEL
rakam_systems-0.1.4.dist-info/RECORD
