Metadata-Version: 2.1
Name: rakam-systems
Version: 0.1.4
Summary: 
Author: MohammedJassem
Author-email: mohammedjassemhlel@gmail.com
Requires-Python: >=3.8.1,<4.0.0
Classifier: Programming Language :: Python :: 3
Classifier: Programming Language :: Python :: 3.9
Classifier: Programming Language :: Python :: 3.10
Classifier: Programming Language :: Python :: 3.11
Classifier: Programming Language :: Python :: 3.12
Requires-Dist: beautifulsoup4 (==4.12.3)
Requires-Dist: channels (==4.0.0)
Requires-Dist: colorlog (==6.8.2)
Requires-Dist: drf-spectacular (==0.27.1)
Requires-Dist: faiss-cpu (==1.8.0.post1)
Requires-Dist: joblib (==1.4.2)
Requires-Dist: openai (==1.37.0)
Requires-Dist: panda (==0.3.1)
Requires-Dist: pandas (==1.3.5)
Requires-Dist: playwright (==1.45.0)
Requires-Dist: pre-commit (==3.5.0)
Requires-Dist: psycopg2-binary (==2.9.9)
Requires-Dist: pymupdf (==1.24.11)
Requires-Dist: pymupdf4llm (==0.0.17)
Requires-Dist: python-dotenv (==1.0.1)
Requires-Dist: python-magic (==0.4.27)
Requires-Dist: requests (==2.31.0)
Requires-Dist: sentence-transformers (==2.6.1)
Requires-Dist: torch (==2.2.2)
Requires-Dist: tqdm (==4.66.4)
